setup.cfg
setup.py
djes/__init__.py
djes/apps.py
djes/factory.py
djes/mapping.py
djes/models.py
djes/search.py
djes/signals.py
djes.egg-info/PKG-INFO
djes.egg-info/SOURCES.txt
djes.egg-info/dependency_links.txt
djes.egg-info/requires.txt
djes.egg-info/top_level.txt
djes/augment/__init__.py
djes/augment/iterators.py
djes/augment/validators.py
djes/augment/wrappers.py
djes/conf/__init__.py
djes/conf/defaults.py
djes/management/__init__.py
djes/management/commands/__init__.py
djes/management/commands/bulk_index.py
djes/management/commands/sync_es.py
djes/utils/__init__.py
djes/utils/query.py
djes/utils/test.py