Metadata-Version: 1.0
Name: djes
Version: 0.1.113
Summary: Connecting Django and elasticsearch-dsl
Home-page: https://github.com/theonion/djes
Author: Chris Sinchok
Author-email: csinchok@theonion.com
License: MIT
Platform: UNKNOWN
